Workbook

Sheet Overview
A1: Solvay Spark Spine AI – Microsoft Azure Bill of Materials
A2: Prepared 2026-10-06 · Source: solvay-spark-spine repo (compose.yml, requirements.txt, docs/system-diagram.md, docs/deployment.md) and Microsoft Learn
A4: Purpose | B4: Map every component of the current containerised application to Microsoft Azure services and list the Azure services to procure.
A5: Recommended target | B5: Azure Container Apps + Azure Database for PostgreSQL Flexible Server (pgvector + Apache AGE) + Microsoft Foundry (Anthropic Claude, Azure OpenAI embeddings) + Azure AI Content Safety + Blob Storage + Microsoft Entra ID + Key Vault + Azure Monitor.
A6: Key advantage vs SAP BTP | B6: Near lift-and-shift: PostgreSQL + pgvector stays PostgreSQL; Neo4j can move into the same server via Apache AGE (openCypher); Claude (Opus 5/5.5, Sonnet 5/5.5, Haiku 4.5) is available natively in Microsoft Foundry, so the Anthropic Messages API is kept.
A7: Commercial model | B7: Azure consumption (Enterprise Agreement / MCA, optionally MACC). Claude in Foundry is billed through Azure Marketplace (Anthropic is the seller); CSP subscriptions are NOT eligible for Claude. Unit prices are Azure retail list prices (West Europe, EUR) pulled 2026-10-06 from the Azure Retail Prices API – before EA/MACC discounts, reservations, savings plans and VAT.
A9: Sheets
A10: Component Mapping | B10: Current component → Azure component, with the change required.
A11: BOM | B11: Services to procure, SKU, Dev/Prod quantities and monthly/annual cost, linked to Price Sources and LLM Usage.
A12: Price Sources | B12: Every Azure retail meter used, with its EUR price and source.
A13: LLM Usage | B13: Claude token-cost model per application flow (models taken from the code; volumes are assumptions to edit).
A14: Re-engineering | B14: Work items needed to port the application, with effort estimates.
A15: Assumptions | B15: Sizing basis and open points to verify with Microsoft.
A17: How to fill in (legend)
A18: Yellow cell, blue text | B18: Input: edit these (BOM quantities, Price Sources prices, LLM Usage volumes and token counts). Example: Ask RAG runs/month 1500 = 1,500 questions per month.
A19: Black text | B19: Formula: do not overwrite (monthly and annual cost, totals).

Sheet Component Mapping
A1: Component mapping: current stack → Microsoft Azure
A2: One row per current component
A4: # | B4: Layer | C4: Current component | D4: Role in application | E4: Azure component | F4: Change needed / notes | G4: Effort (L/M/H)
A5: 1 | B5: Presentation | C5: React SPA (Vite, MUI), served by FastAPI | D5: Extract, Ask, Graph, Evidence, InsightLens, Fit-Gap Copilot pages | E5: Served by the app container (as today), or Azure Static Web Apps | F5: No change required; Static Web Apps optional for CDN/edge caching. | G5: L
A6: 2 | B6: Application | C6: FastAPI backend (backend/api), uvicorn :8000 | D6: REST + SSE API, orchestration | E6: Azure Container Apps (Dedicated D4/D8 workload profile) | F6: Same image as today. Alternative: AKS if Solvay standardises on Kubernetes. | G6: L
A7: 3 | B7: Ingestion | C7: Docling + Tesseract OCR + OpenCV table/flow CV (backend/ingestion) | D7: Documents → Markdown | E7: Azure Container Apps (worker app / Container Apps Jobs); optional serverless GPU (T4) | F7: Keep Docling. Optional complement: Azure AI Document Intelligence (Layout) for scanned PDFs. | G7: L
A8: 4 | B8: Ingestion | C8: Cloud VLM – OpenAI / Claude vision (optional) | D8: Reads images inside documents | E8: Microsoft Foundry – Azure OpenAI GPT vision models or Claude | F8: Point vlm_api.py at Foundry endpoints (Entra ID auth). | G8: L
A9: 5 | B9: AI / LLM | C9: Anthropic Claude (Opus / Sonnet / Haiku) | D9: Answers, agent tool loops, NL→Cypher, Ragas judge, scope classifier | E9: Microsoft Foundry – Claude models (Hosted on Azure: Opus 5.5, Opus 5, Sonnet 5.5, Sonnet 5, Haiku 4.5) | F9: Keep the Anthropic Messages API; change base URL + auth (Entra ID / key). Global Standard deployment (Data Zone only in US). | G9: L
A10: 6 | B10: AI / LLM | C10: Ollama + bge-m3 (1024-d) | D10: Embeddings | E10: Azure OpenAI text-embedding-3-large / -small in Foundry; or bge-m3 on Container Apps serverless GPU / Foundry managed compute | F10: Keeping bge-m3 avoids a re-embed (restore the existing dump). Switching model requires a full re-index. | G10: L
A11: 7 | B11: Data | C11: PostgreSQL 18 + pgvector + full-text/BM25 (rag_documents, rag_chunks) | D11: Hybrid vector + keyword retrieval | E11: Azure Database for PostgreSQL – Flexible Server (PG 18, pgvector, optional pg_diskann) | F11: Lift-and-shift: pg_restore the existing dump; allow-list the vector extension. Alternative: Azure AI Search (hybrid + semantic ranker). | G11: L
A12: 8 | B12: Data | C12: PostgreSQL run stores (agent runs, Ragas scores, users) | D12: History and state | E12: Azure Database for PostgreSQL – Flexible Server (same server) | F12: No change. | G12: L
A13: 9 | B13: Data | C13: docling_session DB (one schema per upload) | D13: Isolated session attachments | E13: Azure Database for PostgreSQL – Flexible Server (second database) | F13: App creates the database: grant CREATEDB to the app role (no superuser on Azure PG). | G13: L
A14: 10 | B14: Graph | C14: Neo4j 5 Community + APOC | D14: Graph copy, Cypher view | E14: Apache AGE extension on the same PostgreSQL Flexible Server (openCypher); or Neo4j AuraDB via Azure Marketplace | F14: AGE: rewrite loader, wrap queries in cypher() SQL, no APOC. AuraDB: zero code change, extra licence. | G14: M
A15: 11 | B15: Storage | C15: knowledge_graph.json, Markdown corpus (solvay-spark/, knowledge_base/), .workdir renders | D15: File storage | E15: Azure Files (mounted into Container Apps) + Azure Blob Storage | F15: Azure Files keeps the current file-path code; Blob for archive/backups. Optionally SharePoint as corpus source. | G15: L
A16: 12 | B16: Agents | C16: Evidence Agent, InsightLens, Fit-Gap Copilot (custom tool-use loops) | D16: Core business logic | E16: Azure Container Apps + Microsoft Foundry | F16: Keep code. Optionally publish to Microsoft Teams / M365 Copilot via Foundry Agent Service or Copilot Studio later. | G16: L
... A23: 19 | B23: Network | C23: TLS reverse proxy (not yet in place) | D23: HTTPS ingress | E23: Container Apps ingress (managed certificates) + Azure Front Door Premium with WAF | F23: Private endpoints for PostgreSQL, Storage, Key Vault, Foundry inside a VNet. | G23: L
A24: 20 | B24: DevOps | C24: reg.ivolve.cloud registry, docker-publish.sh | D24: Build and ship | E24: Azure Container Registry + GitHub Actions or Azure DevOps Pipelines | G24: L
A25: 21 | B25: Application | C25: Exports: WeasyPrint PDF, python-docx, openpyxl | D25: Workshop pack exports | E25: Keep in container; optionally save to SharePoint / OneDrive via Microsoft Graph | G25: L
A26: 22 | B26: Integration | C26: (Future) BPML / S/4 sources | D26: Process hierarchy, As-Is | E26: Azure Logic Apps (SAP connector) + on-premises data gateway; or Azure API Management | F26: Pull BPML and Global Template directly instead of file exports. | G26: M
A27: 23 | B27: Operations | C27: docker logs, /api/health | D27: Monitoring | E27: Azure Monitor, Log Analytics, alerts, Microsoft Defender for Cloud | F27: Diagnostic settings → Log Analytics for audit. | G27: L

Sheet BTP vs Azure
A1: Component mapping: current stack → SAP BTP vs Microsoft Azure
A2: Same mapping in both workbooks (see also sap-btp-bom.xlsx). Effort: L = configuration only, M = moderate code change, H = significant rework.
A4: # | B4: Layer | C4: Current component | D4: Role | E4: SAP BTP component | F4: BTP effort | G4: Microsoft Azure component | H4: Azure effort
A5: 1 | B5: Presentation | C5: React SPA (Vite, MUI) | D5: Web UI | E5: HTML5 Application Repository + Managed Approuter (SAP Build Work Zone) | F5: L | G5: Served by the app container, or Azure Static Web Apps | H5: L
A6: 2 | B6: Application | C6: FastAPI backend (uvicorn :8000) | D6: REST + SSE API | E6: SAP BTP, Kyma runtime (container) | F6: L | G6: Azure Container Apps (Dedicated D8) | H6: L
A7: 3 | B7: Ingestion | C7: Docling + Tesseract OCR + OpenCV | D7: Documents → Markdown | E7: Kyma runtime (optional GPU node pool) | F7: L | G7: Azure Container Apps (optional serverless T4 GPU) | H7: L
A8: 4 | B8: Ingestion | C8: Cloud VLM (OpenAI / Claude vision) | D8: Reads images in documents | E8: Generative AI Hub (SAP AI Core) vision models | F8: L | G8: Microsoft Foundry (GPT vision / Claude) | H8: L
A9: 5 | B9: AI / LLM | C9: Anthropic Claude (Opus / Sonnet / Haiku) | D9: Answers, agents, NL→Cypher, judge, scope check | E9: Generative AI Hub – Claude via Bedrock partner models + Orchestration service | F9: M | G9: Microsoft Foundry – Claude (Hosted on Azure), same Anthropic Messages API | H9: L
A10: 6 | B10: AI / LLM | C10: Ollama + bge-m3 (1024-d) | D10: Embeddings | E10: HANA Cloud VECTOR_EMBEDDING() or GenAI Hub embeddings – full re-embed | F10: M | G10: Keep bge-m3 on Container Apps (no re-embed), or Azure OpenAI text-embedding-3-large | H10: L
A11: 7 | B11: Data | C11: PostgreSQL 18 + pgvector + BM25 | D11: Hybrid retrieval | E11: SAP HANA Cloud – Vector Engine + full-text index (SQL port) | F11: H | G11: Azure Database for PostgreSQL Flexible Server (restore existing dump) | H11: L
A12: 8 | B12: Data | C12: Postgres run stores | D12: Run history, scores, users | E12: SAP HANA Cloud (HDI container) | F12: M | G12: PostgreSQL Flexible Server (same server) | H12: L
A13: 9 | B13: Data | C13: docling_session DB (schema per upload) | D13: Isolated session uploads | E13: HANA Cloud schema or session-keyed tables (redesign) | F13: M | G13: PostgreSQL Flexible Server – second database | H13: L
A14: 10 | B14: Graph | C14: Neo4j 5 Community + APOC | D14: Graph copy, Cypher view | E14: HANA Cloud Graph Engine (openCypher subset) or Knowledge Graph Engine (SPARQL) | F14: H | G14: Apache AGE on PostgreSQL (openCypher), or Neo4j AuraDB (Marketplace) | H14: M
A15: 11 | B15: Storage | C15: Markdown corpus, knowledge_graph.json, .workdir | D15: File storage | E15: SAP Object Store or Document Management Service | F15: M | G15: Azure Files (mounted) + Blob Storage | H15: L
A16: 12 | B16: Agents | C16: Evidence Agent, InsightLens, Fit-Gap Copilot | D16: Agent logic | E16: Kyma + Generative AI Hub (optional Joule Studio later) | F16: L | G16: Container Apps + Microsoft Foundry (optional Teams / Copilot Studio later) | H16: L
... A27: 23 | B27: Operations | C27: docker logs, /api/health | D27: Monitoring and audit | E27: Cloud Logging, Alert Notification, Cloud ALM, Audit Log service | F27: L | G27: Azure Monitor / Log Analytics, alerts, Defender for Cloud | H27: L
D29: Count of components
D30: Low effort | F30: =COUNTIF(F5:F27,"L") -> 11 | H30: =COUNTIF(H5:H27,"L") -> 18
D31: Medium effort | F31: =COUNTIF(F5:F27,"M") -> 10 | H31: =COUNTIF(H5:H27,"M") -> 5
D32: High effort | F32: =COUNTIF(F5:F27,"H") -> 2 | H32: =COUNTIF(H5:H27,"H") -> 0
A34: Key difference: Azure is close to a lift-and-shift (Postgres, pgvector, bge-m3 and the Anthropic API all stay); SAP BTP needs a HANA port, a re-embed, a graph migration and an AI Core LLM client. Re-engineering estimate ≈ 11 person-weeks (Azure) vs 17.5 (BTP).

Sheet BOM
A1: Bill of materials – Microsoft Azure services
A2: West Europe · EUR · retail list prices (2026-10-06). Unit price per unit per month links to Price Sources / LLM Usage; quantities are sizing starting points.
A3: Currency | B3: EUR
A5: Line | B5: Category | C5: Azure service | D5: SKU / tier | E5: Unit (per month) | F5: Required? | G5: Maps current component(s) | H5: Dev qty | I5: Prod qty | J5: Unit price / month | K5: Monthly cost | L5: Annual cost | M5: Sizing / pricing note
A6: 1 | B6: Compute | C6: Azure Container Apps – Dedicated node | D6: D8 (8 vCPU / 32 GiB) | E6: Node | F6: Required | G6: FastAPI, Docling ingestion, agents, Hindsight | H6: 1 | I6: 2 | J6: =(8*'Price Sources'!$D$7+32*'Price Sources'!$D$8)*'Price Sources'!$B$3 -> 551.296 | K6: =(H6+I6)*J6 -> 1653.888 | L6: =K6*12 -> 19846.656 | M6: Prod 2 nodes for HA; Dev 1 node.
A7: 2 | B7: Compute | C7: Azure Container Apps – Dedicated plan management | D7: Per environment | E7: Environment | F7: Required | G7: Container Apps environment | H7: 1 | I7: 1 | J7: ='Price Sources'!$D$9*'Price Sources'!$B$3 -> 64.24 | K7: =(H7+I7)*J7 -> 128.48 | L7: =K7*12 -> 1541.76
A8: 3 | B8: Compute | C8: Azure Container Apps – serverless GPU | D8: Consumption-GPU-NC8as-T4 | E8: GPU-hour | F8: Optional | G8: Docling / OCR acceleration | H8: 0 | I8: 0 | K8: =(H8+I8)*J8 -> 0 | L8: =K8*12 -> 0 | M8: Not priced: API meter rounds to 0.0001 EUR/s; price in calculator if needed.
A9: 4 | B9: Database | C9: PostgreSQL Flexible Server – Dev | D9: Burstable B2ms, PG 18 | E9: Server | F9: Required | G9: PostgreSQL + pgvector, run stores, session DB, Hindsight DB, AGE graph | H9: 1 | I9: 0 | J9: ='Price Sources'!$D$11*'Price Sources'!$B$3 -> 102.273 | K9: =(H9+I9)*J9 -> 102.273 | L9: =K9*12 -> 1227.276
A10: 5 | B10: Database | C10: PostgreSQL Flexible Server – Prod | D10: General Purpose D4ds_v5 (4 vCore/16 GB), PG 18 | E10: Server | F10: Required | G10: As above | H10: 0 | I10: 1 | J10: ='Price Sources'!$D$10*'Price Sources'!$B$3 -> 272.363 | K10: =(H10+I10)*J10 -> 272.363 | L10: =K10*12 -> 3268.356
A11: 6 | B11: Database | C11: PostgreSQL Flexible Server – zone-redundant HA standby | D11: D4ds_v5 | E11: Server | F11: Optional | G11: Production resilience | H11: 0 | I11: 1 | J11: ='Price Sources'!$D$10*'Price Sources'!$B$3 -> 272.363 | K11: =(H11+I11)*J11 -> 272.363 | L11: =K11*12 -> 3268.356 | M11: Standby billed at the primary's compute rate.
A12: 7 | B12: Database | C12: PostgreSQL Flexible Server – storage | D12: Premium SSD | E12: GB | F12: Required | G12: Corpus index, embeddings, run history | H12: 64 | I12: 256 | J12: ='Price Sources'!$D$12 -> 0.1205 | K12: =(H12+I12)*J12 -> 38.56 | L12: =K12*12 -> 462.72 | M12: Backup storage up to 100% of provisioned size included.
A13: 8 | B13: AI | C13: Microsoft Foundry – Anthropic Claude (Opus 5 / Sonnet 5 / Haiku 4.5) | D13: Global Standard | E13: Monthly token spend (LLM Usage) | F13: Required | G13: Answers, agents, NL→Cypher, Ragas judge, guardrails, Hindsight, vision | H13: 0.1 | I13: 1 | J13: ='LLM Usage'!$H$21 -> 409.332 | K13: =(H13+I13)*J13 -> 450.2652 | L13: =K13*12 -> 5403.1824 | M13: Unit = Prod monthly spend from LLM Usage; Dev qty 0.1 = 10% of Prod volume. Billed via Azure Marketplace.
A14: 9 | B14: AI | C14: Microsoft Foundry – Azure OpenAI embeddings | D14: text-embedding-3-large | E14: 1M tokens | F14: Optional | G14: Only if replacing bge-m3 | H14: 0 | I14: 0 | J14: ='Price Sources'!$D$22*1000 -> 0.1 | K14: =(H14+I14)*J14 -> 0 | L14: =K14*12 -> 0 | M14: Re-index of corpus is a one-off; set qty if chosen.
A15: 10 | B15: AI | C15: Azure AI Content Safety | D15: Standard | E15: 1K text records | F15: Required | G15: Guardrails – prompt shields, harm filters | H15: 1 | I15: 5 | J15: ='Price Sources'!$D$20 -> 0.33 | K15: =(H15+I15)*J15 -> 1.98 | L15: =K15*12 -> 23.76 | M15: Prod ~5,000 text records/month.
A16: 11 | B16: AI | C16: Azure AI Language – PII detection | D16: S | E16: 1K text records | F16: Optional | G16: Contact-detail redactor | H16: 0 | I16: 0 | K16: =(H16+I16)*J16 -> 0 | L16: =K16*12 -> 0 | M16: Not priced (tiered); regex redactor can stay.
A17: 12 | B17: AI | C17: Azure AI Document Intelligence | D17: S0 – Layout | E17: 1K pages | F17: Optional | G17: Complement to Tesseract OCR | H17: 0 | I17: 0 | K17: =(H17+I17)*J17 -> 0 | L17: =K17*12 -> 0 | M17: Not priced.
A18: 13 | B18: Storage | C18: Azure Files | D18: Premium, ZRS | E18: GB provisioned | F18: Required | G18: Markdown corpus, knowledge_base, graph JSON, .workdir | H18: 50 | I18: 100 | J18: ='Price Sources'!$D$13 -> 0.2112 | K18: =(H18+I18)*J18 -> 31.68 | L18: =K18*12 -> 380.16
A19: 14 | B19: Storage | C19: Azure Blob Storage | D19: Hot, ZRS | E19: GB | F19: Required | G19: Uploads archive, exports, backups | H19: 25 | I19: 100 | J19: ='Price Sources'!$D$14 -> 0.0211 | K19: =(H19+I19)*J19 -> 2.6375 | L19: =K19*12 -> 31.65 | M19: Transactions negligible at this volume.
A20: 15 | B20: Registry | C20: Azure Container Registry | D20: Standard | E20: Registry | F20: Required | G20: reg.ivolve.cloud | H20: 1 | I20: 0 | J20: ='Price Sources'!$D$15*'Price Sources'!$B$3/24 -> 17.842417 | K20: =(H20+I20)*J20 -> 17.842417 | L20: =K20*12 -> 214.109 | M20: One registry serves both environments.
A21: 16 | B21: Security | C21: Microsoft Entra ID | D21: P1 | E21: User | F21: Required | G21: Sign-in / roles | H21: 0 | I21: 0 | K21: =(H21+I21)*J21 -> 0 | L21: =K21*12 -> 0 | M21: Assumed already licensed by Solvay.
A22: 17 | B22: Security | C22: Azure Key Vault | D22: Standard | E22: 10K operations | F22: Required | G22: .env secrets | H22: 5 | I22: 20 | J22: ='Price Sources'!$D$16 -> 0.0264 | K22: =(H22+I22)*J22 -> 0.66 | L22: =K22*12 -> 7.92
A23: 18 | B23: Network | C23: Azure Front Door | D23: Premium (WAF + Private Link) | E23: Profile | F23: Required | G23: TLS reverse proxy | H23: 0 | I23: 1 | J23: ='Price Sources'!$D$17 -> 290.3907 | K23: =(H23+I23)*J23 -> 290.3907 | L23: =K23*12 -> 3484.6884 | M23: Base fee only; request and data transfer charges small at this volume.
A24: 19 | B24: Network | C24: Private Endpoints | D24: Standard | E24: Endpoint | F24: Required | G24: PostgreSQL, Files, Blob, Key Vault, Foundry | H24: 4 | I24: 5 | J24: ='Price Sources'!$D$18*'Price Sources'!$B$3 -> 6.424 | K24: =(H24+I24)*J24 -> 57.816 | L24: =K24*12 -> 693.792 | M24: Data processed charges excluded.
A25: 20 | B25: Operations | C25: Log Analytics + Application Insights | D25: Pay-as-you-go | E25: GB ingested | F25: Required | G25: Traces, container logs, audit | H25: 5 | I25: 30 | J25: ='Price Sources'!$D$19 -> 2.6311 | K25: =(H25+I25)*J25 -> 92.0885 | L25: =K25*12 -> 1105.062 | M25: First 5 GB/month per billing account free – not deducted.
A26: 21 | B26: Operations | C26: Microsoft Defender for Containers | D26: Standard | E26: vCore | F26: Optional | G26: Security posture | H26: 0 | I26: 16 | J26: ='Price Sources'!$D$21*'Price Sources'!$B$3 -> 6.059 | K26: =(H26+I26)*J26 -> 96.944 | L26: =K26*12 -> 1163.328 | M26: Prod 2 × 8 vCPU nodes.
A27: 22 | B27: Operations | C27: Self-hosted Langfuse on Container Apps | D27: Runs on existing nodes + PostgreSQL | E27: Instance | F27: Optional | G27: Keep Langfuse UX inside Azure | H27: 0 | I27: 1 | K27: =(H27+I27)*J27 -> 0 | L27: =K27*12 -> 0 | M27: Fits in the D8 nodes; no extra cost assumed.
A28: 23 | B28: DevOps | C28: GitHub Actions / Azure DevOps Pipelines | D28: Standard | E28: Parallel job | F28: Required | G28: docker-publish.sh pipeline | H28: 1 | I28: 0 | K28: =(H28+I28)*J28 -> 0 | L28: =K28*12 -> 0 | M28: Usually already licensed.
A29: 24 | B29: Integration | C29: Azure Logic Apps + on-premises data gateway | D29: Standard | E29: Workflow | F29: Optional | G29: Future SAP back-end feeds | H29: 0 | I29: 0 | K29: =(H29+I29)*J29 -> 0 | L29: =K29*12 -> 0 | M29: Only if integrating SAP back-ends.
A30: 25 | B30: Graph | C30: Neo4j AuraDB Professional (Azure Marketplace) | D30: Professional | E30: Instance | F30: Alternative | G30: Neo4j without code change | H30: 0 | I30: 0 | K30: =(H30+I30)*J30 -> 0 | L30: =K30*12 -> 0 | M30: Instead of Apache AGE.
A31: 26 | B31: Search | C31: Azure AI Search | D31: Basic / S1 | E31: Search unit | F31: Alternative | G31: Alternative to pgvector hybrid search | H31: 0 | I31: 0 | K31: =(H31+I31)*J31 -> 0 | L31: =K31*12 -> 0 | M31: Only if replacing in-database retrieval.
J33: Total – Required | K33: =SUMIFS(K6:K31,$F$6:$F$31,"Required") -> 3140.9243 | L33: =SUMIFS(L6:L31,$F$6:$F$31,"Required") -> 37691.092
J34: Total – Optional | K34: =SUMIFS(K6:K31,$F$6:$F$31,"Optional") -> 369.307 | L34: =SUMIFS(L6:L31,$F$6:$F$31,"Optional") -> 4431.684
J35: Total – all lines (excl. Alternative) | K35: =SUM(K6:K31)-SUMIFS(K6:K31,$F$6:$F$31,"Alternative") -> 3510.2313 | L35: =SUM(L6:L31)-SUMIFS(L6:L31,$F$6:$F$31,"Alternative") -> 42122.776
A37: Green = linked from Price Sources / LLM Usage. Yellow price cells = not priced (tiered, licensed or optional) – enter a figure if the line is selected. Retail list prices before discounts, reservations, savings plans and VAT.

Sheet Price Sources
A1: Azure retail price sources
A2: Azure Retail Prices API, region West Europe (EU West), currency EUR, retrieved 2026-10-06. Blue/yellow cells are editable.
A3: Hours per month | B3: 730 | C3: Azure standard billing month (730 h)
A4: USD → EUR factor | B4: 0.88 | C4: Derived from Azure retail list: Log Analytics ingestion EUR 2.6311 / USD 2.99 (West Europe)
A6: ID | B6: Service | C6: Meter / SKU | D6: Retail price (EUR) | E6: Unit of measure | F6: Source
A7: P01 | B7: Azure Container Apps | C7: Dedicated vCPU Usage | D7: 0.0712 | E7: per vCPU-hour | F7: Azure Retail Prices API, westeurope, EUR
A8: P02 | B8: Azure Container Apps | C8: Dedicated Memory Usage | D8: 0.0058 | E8: per GiB-hour | F8: Azure Retail Prices API, westeurope, EUR
A9: P03 | B9: Azure Container Apps | C9: Dedicated Plan Management | D9: 0.088 | E9: per hour (per environment) | F9: Azure Retail Prices API, westeurope, EUR
A10: P04 | B10: Azure Database for PostgreSQL | C10: Flexible Server GP Ddsv5 – Standard_D4ds_v5 (4 vCore) | D10: 0.3731 | E10: per hour | F10: Azure Retail Prices API, westeurope, EUR
A11: P05 | B11: Azure Database for PostgreSQL | C11: Flexible Server Burstable – B2ms | D11: 0.1401 | E11: per hour | F11: Azure Retail Prices API, westeurope, EUR
A12: P06 | B12: Azure Database for PostgreSQL | C12: Flex Server Storage – Data Stored | D12: 0.1205 | E12: per GB-month | F12: Azure Retail Prices API, westeurope, EUR
A13: P07 | B13: Storage – Azure Files | C13: Premium Files – Premium ZRS Provisioned | D13: 0.2112 | E13: per GB-month | F13: Azure Retail Prices API, westeurope, EUR
A14: P08 | B14: Storage – Blob | C14: General Block Blob v2 – Hot ZRS Data Stored (first tier) | D14: 0.0211 | E14: per GB-month | F14: Azure Retail Prices API, westeurope, EUR
A15: P09 | B15: Container Registry | C15: Standard Registry Unit | D15: 0.5866 | E15: per day | F15: Azure Retail Prices API, westeurope, EUR
A16: P10 | B16: Key Vault | C16: Standard – Operations | D16: 0.0264 | E16: per 10K operations | F16: Azure Retail Prices API, westeurope, EUR
A17: P11 | B17: Azure Front Door | C17: Premium Base Fees | D17: 290.3907 | E17: per month | F17: Azure Retail Prices API, Zone 1, EUR
A18: P12 | B18: Virtual Network Private Link | C18: Standard Private Endpoint | D18: 0.0088 | E18: per endpoint-hour | F18: Azure Retail Prices API, Global, EUR
... A22: P16 | B22: Azure OpenAI | C22: text-embedding-3-large (Global) Tokens – API shows 0.0001 (rounded) | D22: 0.0001 | E22: per 1K tokens | F22: Azure Retail Prices API, swedencentral, EUR

Sheet LLM Usage
A1: Claude token-cost model (Microsoft Foundry)
A2: Models per flow come from the code (backend/*). Volumes and tokens per run are ASSUMPTIONS – replace with Langfuse token history.
A4: Model | B4: Input USD / 1M tokens | C4: Output USD / 1M tokens | D4: Source
A5: claude-opus-5 | B5: 5 | C5: 25 | D5: Anthropic standard API rates; Foundry bills Claude via Azure Marketplace at standard rates (also backend/core/pricing.py)
A6: claude-sonnet-5 | B6: 2 | C6: 10 | D6: Anthropic standard API rates; Foundry bills Claude via Azure Marketplace at standard rates (also backend/core/pricing.py)
A7: claude-haiku-4-5 | B7: 1 | C7: 5 | D7: Anthropic standard API rates; Foundry bills Claude via Azure Marketplace at standard rates (also backend/core/pricing.py)
A10: Flow | B10: Code / env var | C10: Model | D10: Runs / month | E10: Input tokens / run | F10: Output tokens / run | G10: Monthly cost (USD) | H10: Monthly cost (EUR) | I10: Basis
A11: Ask RAG answer | B11: rag.py · RAG_ANSWER_MODEL | C11: claude-opus-5 | D11: 1500 | E11: 12000 | F11: 1500 | G11: =D11*(E11*INDEX($B$5:$B$7,MATCH(C11,$A$5:$A$7,0))+F11*INDEX($C$5:$C$7,MATCH(C11,$A$5:$A$7,0)))/1000000 -> 146.25 | H11: =G11*'Price Sources'!$B$4 -> 128.7 | I11: Assumption: ~75 questions/working day; top chunks ≈ 12k tokens
A12: Ragas answer scoring (judge) | B12: rag/evaluation.py · RAG_EVAL_MODEL | C12: claude-sonnet-5 | D12: 1500 | E12: 20000 | F12: 2000 | G12: =D12*(E12*INDEX($B$5:$B$7,MATCH(C12,$A$5:$A$7,0))+F12*INDEX($C$5:$C$7,MATCH(C12,$A$5:$A$7,0)))/1000000 -> 90 | H12: =G12*'Price Sources'!$B$4 -> 79.2 | I12: Assumption: one scoring per Ask answer, nine judges
A13: Scope guardrail classifier | B13: guardrails/scope.py · AGENT_SCOPE_MODEL | C13: claude-haiku-4-5 | D13: 2000 | E13: 1500 | F13: 100 | G13: =D13*(E13*INDEX($B$5:$B$7,MATCH(C13,$A$5:$A$7,0))+F13*INDEX($C$5:$C$7,MATCH(C13,$A$5:$A$7,0)))/1000000 -> 4 | H13: =G13*'Price Sources'!$B$4 -> 3.52 | I13: Assumption: only requests the domain signals don't settle
A14: Evidence Agent | B14: agents/evidence · EVIDENCE_MODEL | C14: claude-opus-5 | D14: 200 | E14: 80000 | F14: 6000 | G14: =D14*(E14*INDEX($B$5:$B$7,MATCH(C14,$A$5:$A$7,0))+F14*INDEX($C$5:$C$7,MATCH(C14,$A$5:$A$7,0)))/1000000 -> 110 | H14: =G14*'Price Sources'!$B$4 -> 96.8 | I14: Assumption: multi-turn tool loop
A15: InsightLens (fit-gap register) | B15: agents/fitgap · FITGAP_MODEL | C15: claude-opus-5 | D15: 40 | E15: 150000 | F15: 15000 | G15: =D15*(E15*INDEX($B$5:$B$7,MATCH(C15,$A$5:$A$7,0))+F15*INDEX($C$5:$C$7,MATCH(C15,$A$5:$A$7,0)))/1000000 -> 45 | H15: =G15*'Price Sources'!$B$4 -> 39.6 | I15: Assumption: one BPML scope per run
A16: Fit-Gap Copilot | B16: agents/rollout · FITGAP_COPILOT_MODEL | C16: claude-opus-5 | D16: 20 | E16: 120000 | F16: 20000 | G16: =D16*(E16*INDEX($B$5:$B$7,MATCH(C16,$A$5:$A$7,0))+F16*INDEX($C$5:$C$7,MATCH(C16,$A$5:$A$7,0)))/1000000 -> 22 | H16: =G16*'Price Sources'!$B$4 -> 19.36 | I16: ~120k input tokens per run (app UI estimate); 20 runs/month assumed
A17: Web guardrail | B17: guardrails/web.py · AGENT_WEB_MODEL | C17: claude-sonnet-5 | D17: 300 | E17: 4000 | F17: 500 | G17: =D17*(E17*INDEX($B$5:$B$7,MATCH(C17,$A$5:$A$7,0))+F17*INDEX($C$5:$C$7,MATCH(C17,$A$5:$A$7,0)))/1000000 -> 3.9 | H17: =G17*'Price Sources'!$B$4 -> 3.432 | I17: Assumption
A18: NL → Cypher | B18: graph/kg_nl2cypher.py · CYPHER_MODEL | C18: claude-opus-5 | D18: 300 | E18: 6000 | F18: 500 | G18: =D18*(E18*INDEX($B$5:$B$7,MATCH(C18,$A$5:$A$7,0))+F18*INDEX($C$5:$C$7,MATCH(C18,$A$5:$A$7,0)))/1000000 -> 12.75 | H18: =G18*'Price Sources'!$B$4 -> 11.22 | I18: Assumption
A19: Hindsight memory (retain/reflect) | B19: solvay-hindsight · HINDSIGHT_MODEL | C19: claude-opus-5 | D19: 200 | E19: 10000 | F19: 2000 | G19: =D19*(E19*INDEX($B$5:$B$7,MATCH(C19,$A$5:$A$7,0))+F19*INDEX($C$5:$C$7,MATCH(C19,$A$5:$A$7,0)))/1000000 -> 20 | H19: =G19*'Price Sources'!$B$4 -> 17.6 | I19: Assumption: one retain per Evidence run
A20: Vision conversion (optional) | B20: ingestion/vlm_api.py | C20: claude-opus-5 | D20: 500 | E20: 2000 | F20: 500 | G20: =D20*(E20*INDEX($B$5:$B$7,MATCH(C20,$A$5:$A$7,0))+F20*INDEX($C$5:$C$7,MATCH(C20,$A$5:$A$7,0)))/1000000 -> 11.25 | H20: =G20*'Price Sources'!$B$4 -> 9.9 | I20: Assumption: images per month when a cloud VLM is chosen
F21: Total per month | G21: =SUM(G11:G20) -> 465.15 | H21: =SUM(H11:H20) -> 409.332
A23: Prompt caching (cache reads ≈ 10% of input price) and lower effort settings would reduce these figures; not modelled.

Sheet Re-engineering
A1: Re-engineering work items
A2: Effort in person-weeks is a first estimate; refine during planning
A4: # | B4: Work item | C4: Scope | D4: Affected code | E4: Effort (person-weeks) | F4: Risk
A5: 1 | B5: PostgreSQL migration | C5: Provision Flexible Server PG 18, allow-list vector (+ age), restore dump, grant CREATEDB for session DB, Entra auth | D5: backend/rag/rag.py (connection only) | E5: 0.5 | F5: Low
A6: 2 | B6: LLM client to Microsoft Foundry | C6: Point Anthropic SDK at Foundry Claude endpoint, Entra/key auth, deployment names; verify tool use + streaming | D6: backend/agents, backend/rag, backend/graph | E6: 0.5 | F6: Low
A7: 3 | B7: Embeddings | C7: Option A: bge-m3 on Container Apps GPU/CPU (no re-index). Option B: Azure OpenAI embeddings + full re-index | D7: backend/rag | E7: 0.5 | F7: Low
A8: 4 | B8: Graph to Apache AGE | C8: Rewrite loader, wrap Cypher in cypher() SQL, replace APOC, re-prompt NL→Cypher (skip if AuraDB chosen) | D8: backend/graph/kg_neo4j_load.py, kg_nl2cypher.py | E8: 2 | F8: Medium
A9: 5 | B9: Guardrails | C9: Add Content Safety Prompt Shields; optional Language PII for redaction | D9: backend/agents/guardrails | E9: 1 | F9: Low
A10: 6 | B10: Authentication to Entra ID | C10: Container Apps built-in auth or MSAL/JWT in FastAPI; map app roles to Admin/User | D10: backend/api | E10: 1 | F10: Medium
A11: 7 | B11: Storage | C11: Azure Files mounts for corpus, knowledge_base, graph data, workdir | D11: compose.yml → Container Apps config | E11: 0.5 | F11: Low
A12: 8 | B12: Hindsight memory | C12: Point LiteLLM at Foundry Claude; new Container App | D12: Dockerfile.hindsight, env | E12: 0.5 | F12: Low
A13: 9 | B13: Observability | C13: OpenTelemetry → Application Insights, or self-host Langfuse; Foundry evaluations optional | D13: backend/core/tracing.py, evaluation.py | E13: 1 | F13: Low
A14: 10 | B14: Infrastructure as code & CI/CD | C14: Bicep/Terraform for all resources, VNet + private endpoints, ACR, pipelines | D14: Dockerfile, scripts/ | E14: 2 | F14: Medium
A15: 11 | B15: Testing & cut-over | C15: Regression of RAG, agents, Fit-Gap outputs vs current; data migration; UAT | D15: backend/tests | E15: 1.5 | F15: Medium
D16: Total | E16: =SUM(E5:E15) -> 11

Sheet Assumptions
A1: Assumptions and open points
A2: Verify open points with Microsoft before finalising the BOM
A4: # | B4: Type | C4: Item | D4: Source / basis
A5: 1 | B5: Assumption | C5: Current app image is ~3–4 GB with OS packages (LibreOffice, Poppler, Tesseract, pango/cairo) – runs unchanged on Container Apps. | D5: docs/deployment.md, Dockerfile
A6: 2 | B6: Assumption | C6: Knowledge graph ~11k nodes / ~21k relationships – small enough for Apache AGE in the same PostgreSQL server. | D6: compose.neo4j.yml
A7: 3 | B7: Assumption | C7: Render storage ~20 MB per large deck (144 slides), never auto-cleaned. | D7: README.md
A8: 4 | B8: Assumption | C8: Fit-Gap Copilot run ≈ 120k input tokens (basis for Claude token sizing). | D8: Application UI estimate
A9: 5 | B9: Assumption | C9: Prod Container Apps: 2 × D8 nodes; Dev: 1 node. PostgreSQL Prod D4ds_v5, Dev B2ms. | D9: Sizing starting point – to validate under load test
A10: 6 | B10: Assumption | C10: Microsoft Entra ID licences already held by Solvay. | D10: To confirm with Solvay IT
A11: 7 | B11: Assumption | C11: Prices are retail list prices, West Europe, EUR, retrieved 2026-10-06; no EA/MACC discount, reservation, savings plan or VAT applied. | D11: Azure Retail Prices API (prices.azure.com) via Azure MCP plugin
A12: 8 | B12: Assumption | C12: Claude priced at Anthropic standard API rates in USD (Foundry bills via Marketplace at standard rates), converted at the USD→EUR factor on Price Sources. | D12: Anthropic pricing; backend/core/pricing.py
A13: 9 | B13: Assumption | C13: LLM volumes (runs per month, tokens per run) are estimates – replace with Langfuse token history before quoting. | D13: LLM Usage sheet
A14: 10 | B14: Assumption | C14: Dev LLM spend = 10% of Prod volume (Dev qty 0.1 on the Claude BOM line). | D14: Sizing starting point
A15: 11 | B15: Not priced | C15: Serverless T4 GPU, Language PII, Document Intelligence, Entra ID, GitHub/Azure DevOps, Logic Apps, self-hosted Langfuse, AuraDB, AI Search – tiered, licence-based or optional; left blank. | D15: Price in Azure Pricing Calculator if selected
A16: 12 | B16: Fact | C16: Claude Opus 5.5, Opus 5, Sonnet 5.5, Sonnet 5 and Haiku 4.5 are offered in Microsoft Foundry (Hosted on Azure), Global Standard deployment; Data Zone Standard only in the US. | D16: learn.microsoft.com/azure/foundry/foundry-models/concepts/claude-models
... A23: 19 | B23: Open point | C23: Apache AGE vs Neo4j AuraDB for the graph view. | D23: Architecture decision
